passwordgenerator/__init__.py
passwordgenerator/passwordgenerator.py
Generator_pass-0.1.dist-info/METADATA
Generator_pass-0.1.dist-info/WHEEL
Generator_pass-0.1.dist-info/top_level.txt
Generator_pass-0.1.dist-info/RECORD
